{
  "title": "IMG-20200314-WA0013.jpg",
  "description": "",
  "imageViews": "0",
  "creationTime": {
    "timestamp": "1584336128",
    "formatted": "16 Mar 2020, 05:22:08 UTC"
  },
  "photoTakenTime": {
    "timestamp": "1584204954",
    "formatted": "14 Mar 2020, 16:55:54 UTC"
  },
  "geoData": {
    "latitude": 0.0,
    "longitude": 0.0,
    "altitude": 0.0,
    "latitudeSpan": 0.0,
    "longitudeSpan": 0.0
  },
  "geoDataExif": {
    "latitude": 0.0,
    "longitude": 0.0,
    "altitude": 0.0,
    "latitudeSpan": 0.0,
    "longitudeSpan": 0.0
  },
  "people": [{
    "name": "madhuri"
  }],
  "url": "https://lh3.googleusercontent.com/r3cdxt27TUl0opz7gPHW09Iwd80ssVHnTOmvieQmX_AnHU_S7WSvOKpP0vxQyaKdjTHbfsily89N-wEpaNfapu1o-q7vP0GD84ckw7s",
  "googlePhotosOrigin": {
    "mobileUpload": {
      "deviceFolder": {
        "localFolderName": "WhatsApp Images"
      },
      "deviceType": "ANDROID_PHONE"
    }
  },
  "photoLastModifiedTime": {
    "timestamp": "1676600239",
    "formatted": "17 Feb 2023, 02:17:19 UTC"
  }
}