{
  "title": "IMG_20210126_165445060.jpg",
  "description": "",
  "imageViews": "0",
  "creationTime": {
    "timestamp": "1611720378",
    "formatted": "27 Jan 2021, 04:06:18 UTC"
  },
  "photoTakenTime": {
    "timestamp": "1611660285",
    "formatted": "26 Jan 2021, 11:24:45 UTC"
  },
  "geoData": {
    "latitude": 0.0,
    "longitude": 0.0,
    "altitude": 0.0,
    "latitudeSpan": 0.0,
    "longitudeSpan": 0.0
  },
  "geoDataExif": {
    "latitude": 0.0,
    "longitude": 0.0,
    "altitude": 0.0,
    "latitudeSpan": 0.0,
    "longitudeSpan": 0.0
  },
  "people": [{
    "name": "Subodh"
  }, {
    "name": "Naman"
  }, {
    "name": "Pawan"
  }],
  "url": "https://lh3.googleusercontent.com/2dRh3VGG2X8G2ur72ipMyWgOMMJ2CX2WHv5SnYZA8ENTh4VGBX9RrRSzCvsJWLd7gjbU9lAyNiOzFWNBzLUz-dAnbdrC8ZFp-9haKDk",
  "googlePhotosOrigin": {
    "mobileUpload": {
      "deviceFolder": {
        "localFolderName": ""
      },
      "deviceType": "ANDROID_PHONE"
    }
  },
  "photoLastModifiedTime": {
    "timestamp": "1676600243",
    "formatted": "17 Feb 2023, 02:17:23 UTC"
  }
}