{
  "title": "IMG_20200309_094859597.jpg",
  "description": "",
  "imageViews": "1",
  "creationTime": {
    "timestamp": "1583754575",
    "formatted": "9 Mar 2020, 11:49:35 UTC"
  },
  "photoTakenTime": {
    "timestamp": "1583727540",
    "formatted": "9 Mar 2020, 04:19:00 UTC"
  },
  "geoData": {
    "latitude": 0.0,
    "longitude": 0.0,
    "altitude": 0.0,
    "latitudeSpan": 0.0,
    "longitudeSpan": 0.0
  },
  "geoDataExif": {
    "latitude": 0.0,
    "longitude": 0.0,
    "altitude": 0.0,
    "latitudeSpan": 0.0,
    "longitudeSpan": 0.0
  },
  "people": [{
    "name": "Subodh"
  }],
  "url": "https://lh3.googleusercontent.com/WHCLrZl68CjDwwM4jZwX3lx76_DBCBqC4Q9DcyRoOY1xEFiLiaLdZQaImOXXgH0UIrICZLqVN3eAVV0ji8UBWlKIjDfnIzFcB3HlMKk",
  "googlePhotosOrigin": {
    "mobileUpload": {
      "deviceFolder": {
        "localFolderName": ""
      },
      "deviceType": "ANDROID_PHONE"
    }
  },
  "photoLastModifiedTime": {
    "timestamp": "1676600239",
    "formatted": "17 Feb 2023, 02:17:19 UTC"
  }
}