{
  "title": "Snapchat-4536644.jpg",
  "description": "",
  "imageViews": "24",
  "creationTime": {
    "timestamp": "1581417576",
    "formatted": "11 Feb 2020, 10:39:36 UTC"
  },
  "photoTakenTime": {
    "timestamp": "1580988494",
    "formatted": "6 Feb 2020, 11:28:14 UTC"
  },
  "geoData": {
    "latitude": 0.0,
    "longitude": 0.0,
    "altitude": 0.0,
    "latitudeSpan": 0.0,
    "longitudeSpan": 0.0
  },
  "geoDataExif": {
    "latitude": 0.0,
    "longitude": 0.0,
    "altitude": 0.0,
    "latitudeSpan": 0.0,
    "longitudeSpan": 0.0
  },
  "people": [{
    "name": "Naman"
  }],
  "url": "https://lh3.googleusercontent.com/uR6B7KjDbBTnAjfWSzev1zTUUt48JhMWK0YIRUHgCSjupAMwjI1kOOKZwJ8lDGYZmMYL4iYxjR-CXbb_ki3TpRd5719-nz2S5YUjiC4",
  "googlePhotosOrigin": {
    "mobileUpload": {
      "deviceFolder": {
        "localFolderName": "Snapchat"
      },
      "deviceType": "ANDROID_PHONE"
    }
  },
  "photoLastModifiedTime": {
    "timestamp": "1676600239",
    "formatted": "17 Feb 2023, 02:17:19 UTC"
  }
}