{
  "title": "857421057_147683.jpg",
  "description": "",
  "imageViews": "4",
  "creationTime": {
    "timestamp": "1593881994",
    "formatted": "4 Jul 2020, 16:59:54 UTC"
  },
  "photoTakenTime": {
    "timestamp": "1580988762",
    "formatted": "6 Feb 2020, 11:32:42 UTC"
  },
  "geoData": {
    "latitude": 0.0,
    "longitude": 0.0,
    "altitude": 0.0,
    "latitudeSpan": 0.0,
    "longitudeSpan": 0.0
  },
  "geoDataExif": {
    "latitude": 0.0,
    "longitude": 0.0,
    "altitude": 0.0,
    "latitudeSpan": 0.0,
    "longitudeSpan": 0.0
  },
  "people": [{
    "name": "Subodh"
  }, {
    "name": "Naman"
  }],
  "url": "https://lh3.googleusercontent.com/D6Qq9RghR9pjg8UlduEJu3UKqBIdSPyl6Znk0Q2XckwSVNoPDtgfUeC8yONxjen89SVNpO-6UPZoIjbhJHuM4tBfEDmuImq5WFwBmyo",
  "googlePhotosOrigin": {
    "mobileUpload": {
      "deviceFolder": {
        "localFolderName": "image"
      },
      "deviceType": "ANDROID_PHONE"
    }
  },
  "photoLastModifiedTime": {
    "timestamp": "1676600241",
    "formatted": "17 Feb 2023, 02:17:21 UTC"
  }
}