{"color":"DEFAULT","isTrashed":false,"isPinned":false,"isArchived":false,"textContent":"I am an expert on the ground of web development and can do many things related to the job. I am quite adept in coding and markup languages and in creating applications using client server model including\n\n1. Python\n2. HTML/CSS\n3. JavaScript\n4. PHP\n5. Mongodb\n6. MySQL \n\nI am a graduate on Information Technology  and had many certificates related the course-work of web developing. I have intense capability in business related work and those are,\n\n1. Organizer and planner of different project\n2. Freely attend the deadlines\n3. Critically analysis the complex implications related to the job\n4. Extraordinary skill of persuading customers for the betterment of the company.\n\nI have got\n1. 5 star rate to the most of my famous works\n2. Got awarded as the bright pioneer of web developing\n3. Over 320 positive and slaying reviews from my previous clients\n4. High demand on the market of web developing\n\n\nI have always been so devoted to my work and give my level best to any project I take in hand. Thank you.","title":"Freelancer profile ","userEditedTimestampUsec":1663414461770000,"createdTimestampUsec":1663028499148000}